ezdeps/.ezdeps.json
ezdeps/__init__.py
ezdeps/__main__.py
ezdeps/build.py
ezdeps/docs.py
ezdeps/install.py
ezdeps/manager.py
ezdeps/publish.py
ezdeps/uninstall.py
ezdeps/update.py
ezdeps/resources/docs.txt
ezdeps/utils/__init__.py
ezdeps/utils/cli.py
ezdeps/utils/constants.py
ezdeps/utils/merge.py
ezdeps/utils/packages.py
ezdeps-1.2.0.data/scripts/ezdeps
ezdeps-1.2.0.dist-info/LICENSE
ezdeps-1.2.0.dist-info/METADATA
ezdeps-1.2.0.dist-info/WHEEL
ezdeps-1.2.0.dist-info/top_level.txt
ezdeps-1.2.0.dist-info/RECORD
