Metadata-Version: 2.1
Name: ezdeps
Version: 1.2.0
Summary: Package manager for python
Home-page: https://github.com/jellyb0y/easy-deps
Author: Vitaly Kisel <jellyb0y>
Author-email: kisel@internet.ru
License: UNKNOWN
Platform: UNKNOWN
Classifier: Programming Language :: Python :: 3.8
Classifier: License :: OSI Approved :: MIT License
Classifier: Operating System :: OS Independent
Requires-Python: >=3.6
Requires-Dist: pip (>=20.0.0)
Requires-Dist: setuptools (==56.2.0)
Requires-Dist: twine (==3.4.1)
Requires-Dist: wheel (==0.36.2)
